{
  "kind": "singleType",
  "collectionName": "homes",
  "info": {
    "singularName": "home",
    "pluralName": "homes",
    "displayName": "Homepage"
  },
  "options": {
    "draftAndPublish": true
  },
  "pluginOptions": {},
  "attributes": {
    "home_banner": {
      "type": "component",
      "component": "home.home-banner",
      "repeatable": false
    },
    "home_welcome": {
      "type": "component",
      "component": "home.home-welcome",
      "repeatable": false
    },
    "home_story": {
      "type": "component",
      "component": "home.home-story",
      "repeatable": false
    },
    "home_why_choose": {
      "type": "component",
      "component": "home.home-why-choose",
      "repeatable": false
    },
    "home_equipment": {
      "type": "component",
      "component": "home.home-equipment",
      "repeatable": false
    },
    "home_process": {
      "type": "component",
      "component": "home.home-process",
      "repeatable": false
    },
    "home_services": {
      "type": "component",
      "component": "home.home-service",
      "repeatable": false
    },
    "home_experience": {
      "type": "component",
      "component": "home.home-experience",
      "repeatable": false
    },
    "home_products": {
      "type": "component",
      "component": "home.home-product",
      "repeatable": false
    },
    "home_news": {
      "type": "component",
      "component": "home.home-news",
      "repeatable": false
    },
    "home_testimonials": {
      "type": "component",
      "component": "home.home-testimonial",
      "repeatable": false
    },
    "home_contact_banner": {
      "type": "component",
      "component": "shared.contact-banner",
      "repeatable": false
    }
  }
}
